bwrap/__init__.py
bwrap-0.0.0.dist-info/entry_points.txt
bwrap-0.0.0.dist-info/LICENSE
bwrap-0.0.0.dist-info/WHEEL
bwrap-0.0.0.dist-info/METADATA
bwrap-0.0.0.dist-info/RECORD
