Metadata-Version: 2.1
Name: bwrap
Version: 0.0.0
Summary: A basic python binary wrapper.
Author: Mark Beacom
Author-email: m@beacom.dev
Requires-Python: >=3.9,<4.0
Classifier: Programming Language :: Python :: 3
Classifier: Programming Language :: Python :: 3.9
Classifier: Programming Language :: Python :: 3.10
